setup.cfg
setup.py
configurable/__init__.py
configurable.egg-info/PKG-INFO
configurable.egg-info/SOURCES.txt
configurable.egg-info/dependency_links.txt
configurable.egg-info/entry_points.txt
configurable.egg-info/top_level.txt
configurable.egg-info/zip-safe