Metadata-Version: 1.0
Name: configurable
Version: 0.1dev
Summary: configurable - Class integration with config files
Home-page: UNKNOWN
Author: Krister Hedfors
Author-email: krister@hedfors.se
License: UNKNOWN
Keywords: ConfigParser configurable configuration Configfile config conffile
Platform: UNKNOWN
